rogtk-0.1.20.dist-info/METADATA
rogtk-0.1.20.dist-info/WHEEL
rogtk/__init__.py
rogtk/rogtk.abi3.so
rogtk/utils.py
rogtk/utils/utils.py
rogtk-0.1.20.dist-info/RECORD
