Metadata-Version: 2.4
Name: rogtk
Version: 0.1.20
Classifier: Programming Language :: Rust
Classifier: Programming Language :: Python :: Implementation :: CPython
Classifier: Programming Language :: Python :: Implementation :: PyPy
Requires-Dist: polars>=1.25,!=1.26.*
Requires-Dist: pytest>=7.0 ; extra == 'test'
Provides-Extra: test
Summary: Rust-based genomics toolkit - high-performance backend for ogtk
Author-email: Pedro Olivares <pedroy.final@gmail.com>
Maintainer-email: Pedro Olivares <pedroy.final@gmail.com>
License: MIT
Requires-Python: >=3.10
